{"index":{"links":{"/":[{"source":"/","target":"/notes/atomic-notes","text":"atomic notes"},{"source":"/","target":"/content/notes/Sweep-Your-Mind","text":"sweeping"},{"source":"/","target":"/notes/continuous-care","text":"Continuous care"},{"source":"/","target":"/references/Amethyst","text":"Amethyst"},{"source":"/","target":"/journals/_index","text":"Journals"},{"source":"/","target":"/Tasks","text":"Tasks"},{"source":"/","target":"/Today-I-Learned","text":"Today I Learned"},{"source":"/","target":"/references/grammar","text":"Grammar"},{"source":"/","target":"/notes/MPV-Player","text":"MPV Player"},{"source":"/","target":"/references/Python","text":"Python"},{"source":"/","target":"/notes/Sans-serif","text":"Sans-serif"},{"source":"/","target":"/notes/Serif","text":"Serif"},{"source":"/","target":"/references/Skullcandy-Crusher-ANC","text":"Skullcandy Crusher ANC"},{"source":"/","target":"/lists/bookmarklets","text":"Bookmarklets"},{"source":"/","target":"/lists/Inspiration","text":"Inspiration"},{"source":"/","target":"/lists/link-collection","text":"Link Collection"},{"source":"/","target":"/lists/newsletters-collection","text":"Newsletters Collection"},{"source":"/","target":"/lists/podcast-collection","text":"Podcast Collection"},{"source":"/","target":"/lists/quotes-collection","text":"Quotes Collection"},{"source":"/","target":"/lists/Snippets","text":"Snippets"},{"source":"/","target":"/lists/tools-collection","text":"Tools Collection"},{"source":"/","target":"/lists/Wishlist","text":"Wishlist"},{"source":"/","target":"/lists/words-collection","text":"Words Collection"}],"/journals/2023-06-08":[{"source":"/journals/2023-06-08","target":"/docs/projects/","text":"Projects"}],"/journals/2023-06-13":[{"source":"/journals/2023-06-13","target":"/docs/cheatsheet/","text":"Cheat Sheet"}],"/learning/Guitar":[{"source":"/learning/Guitar","target":"/../notes/arpeggio","text":"arpeggio"},{"source":"/learning/Guitar","target":"/../notes/chords","text":"broken chord"}],"/notes/Arpeggio":[{"source":"/notes/Arpeggio","target":"/chords","text":"broken chord"}],"/notes/Continuous-Care":[{"source":"/notes/Continuous-Care","target":"/atomic-notes","text":"atomic"}],"/references/Amethyst":[{"source":"/references/Amethyst","target":"/notes/sans-serif","text":"Sans-serif"},{"source":"/references/Amethyst","target":"/notes/Serif","text":"Serif"}],"/tasks":[{"source":"/tasks","target":"/templates/Journal","text":"Journals"},{"source":"/tasks","target":"/lists/procrastination","text":"Procrastination"},{"source":"/tasks","target":"/Today-I-Learned","text":"Today I Learned"},{"source":"/tasks","target":"/games/_index","text":"Games"},{"source":"/tasks","target":"/lists/life-lessons","text":"Life Lessons"}]},"backlinks":{"/../notes/arpeggio":[{"source":"/learning/Guitar","target":"/../notes/arpeggio","text":"arpeggio"}],"/../notes/chords":[{"source":"/learning/Guitar","target":"/../notes/chords","text":"broken chord"}],"/Tasks":[{"source":"/","target":"/Tasks","text":"Tasks"}],"/Today-I-Learned":[{"source":"/","target":"/Today-I-Learned","text":"Today I Learned"},{"source":"/tasks","target":"/Today-I-Learned","text":"Today I Learned"}],"/atomic-notes":[{"source":"/notes/Continuous-Care","target":"/atomic-notes","text":"atomic"}],"/chords":[{"source":"/notes/Arpeggio","target":"/chords","text":"broken chord"}],"/content/notes/Sweep-Your-Mind":[{"source":"/","target":"/content/notes/Sweep-Your-Mind","text":"sweeping"}],"/docs/cheatsheet/":[{"source":"/journals/2023-06-13","target":"/docs/cheatsheet/","text":"Cheat Sheet"}],"/docs/projects/":[{"source":"/journals/2023-06-08","target":"/docs/projects/","text":"Projects"}],"/games/_index":[{"source":"/tasks","target":"/games/_index","text":"Games"}],"/journals/_index":[{"source":"/","target":"/journals/_index","text":"Journals"}],"/lists/Inspiration":[{"source":"/","target":"/lists/Inspiration","text":"Inspiration"}],"/lists/Snippets":[{"source":"/","target":"/lists/Snippets","text":"Snippets"}],"/lists/Wishlist":[{"source":"/","target":"/lists/Wishlist","text":"Wishlist"}],"/lists/bookmarklets":[{"source":"/","target":"/lists/bookmarklets","text":"Bookmarklets"}],"/lists/life-lessons":[{"source":"/tasks","target":"/lists/life-lessons","text":"Life Lessons"}],"/lists/link-collection":[{"source":"/","target":"/lists/link-collection","text":"Link Collection"}],"/lists/newsletters-collection":[{"source":"/","target":"/lists/newsletters-collection","text":"Newsletters Collection"}],"/lists/podcast-collection":[{"source":"/","target":"/lists/podcast-collection","text":"Podcast Collection"}],"/lists/procrastination":[{"source":"/tasks","target":"/lists/procrastination","text":"Procrastination"}],"/lists/quotes-collection":[{"source":"/","target":"/lists/quotes-collection","text":"Quotes Collection"}],"/lists/tools-collection":[{"source":"/","target":"/lists/tools-collection","text":"Tools Collection"}],"/lists/words-collection":[{"source":"/","target":"/lists/words-collection","text":"Words Collection"}],"/notes/MPV-Player":[{"source":"/","target":"/notes/MPV-Player","text":"MPV Player"}],"/notes/Sans-serif":[{"source":"/","target":"/notes/Sans-serif","text":"Sans-serif"}],"/notes/Serif":[{"source":"/","target":"/notes/Serif","text":"Serif"},{"source":"/references/Amethyst","target":"/notes/Serif","text":"Serif"}],"/notes/atomic-notes":[{"source":"/","target":"/notes/atomic-notes","text":"atomic notes"}],"/notes/continuous-care":[{"source":"/","target":"/notes/continuous-care","text":"Continuous care"}],"/notes/sans-serif":[{"source":"/references/Amethyst","target":"/notes/sans-serif","text":"Sans-serif"}],"/references/Amethyst":[{"source":"/","target":"/references/Amethyst","text":"Amethyst"}],"/references/Python":[{"source":"/","target":"/references/Python","text":"Python"}],"/references/Skullcandy-Crusher-ANC":[{"source":"/","target":"/references/Skullcandy-Crusher-ANC","text":"Skullcandy Crusher ANC"}],"/references/grammar":[{"source":"/","target":"/references/grammar","text":"Grammar"}],"/templates/Journal":[{"source":"/tasks","target":"/templates/Journal","text":"Journals"}]}},"links":[{"source":"/","target":"/notes/atomic-notes","text":"atomic notes"},{"source":"/","target":"/content/notes/Sweep-Your-Mind","text":"sweeping"},{"source":"/","target":"/notes/continuous-care","text":"Continuous care"},{"source":"/","target":"/references/Amethyst","text":"Amethyst"},{"source":"/","target":"/journals/_index","text":"Journals"},{"source":"/","target":"/Tasks","text":"Tasks"},{"source":"/","target":"/Today-I-Learned","text":"Today I Learned"},{"source":"/","target":"/references/grammar","text":"Grammar"},{"source":"/","target":"/notes/MPV-Player","text":"MPV Player"},{"source":"/","target":"/references/Python","text":"Python"},{"source":"/","target":"/notes/Sans-serif","text":"Sans-serif"},{"source":"/","target":"/notes/Serif","text":"Serif"},{"source":"/","target":"/references/Skullcandy-Crusher-ANC","text":"Skullcandy Crusher ANC"},{"source":"/","target":"/lists/bookmarklets","text":"Bookmarklets"},{"source":"/","target":"/lists/Inspiration","text":"Inspiration"},{"source":"/","target":"/lists/link-collection","text":"Link Collection"},{"source":"/","target":"/lists/newsletters-collection","text":"Newsletters Collection"},{"source":"/","target":"/lists/podcast-collection","text":"Podcast Collection"},{"source":"/","target":"/lists/quotes-collection","text":"Quotes Collection"},{"source":"/","target":"/lists/Snippets","text":"Snippets"},{"source":"/","target":"/lists/tools-collection","text":"Tools Collection"},{"source":"/","target":"/lists/Wishlist","text":"Wishlist"},{"source":"/","target":"/lists/words-collection","text":"Words Collection"},{"source":"/journals/2023-06-08","target":"/docs/projects/","text":"Projects"},{"source":"/journals/2023-06-13","target":"/docs/cheatsheet/","text":"Cheat Sheet"},{"source":"/learning/Guitar","target":"/../notes/arpeggio","text":"arpeggio"},{"source":"/learning/Guitar","target":"/../notes/chords","text":"broken chord"},{"source":"/notes/Arpeggio","target":"/chords","text":"broken chord"},{"source":"/notes/Continuous-Care","target":"/atomic-notes","text":"atomic"},{"source":"/references/Amethyst","target":"/notes/sans-serif","text":"Sans-serif"},{"source":"/references/Amethyst","target":"/notes/Serif","text":"Serif"},{"source":"/tasks","target":"/templates/Journal","text":"Journals"},{"source":"/tasks","target":"/lists/procrastination","text":"Procrastination"},{"source":"/tasks","target":"/Today-I-Learned","text":"Today I Learned"},{"source":"/tasks","target":"/games/_index","text":"Games"},{"source":"/tasks","target":"/lists/life-lessons","text":"Life Lessons"}]}